CHANGES.txt
LICENSE.txt
MANIFEST.in
README.txt
setup.py
src/defaultsite/__init__.py
src/defaultsite/management.py
src/defaultsite/settings.py
src/django_defaultsite.egg-info/PKG-INFO
src/django_defaultsite.egg-info/SOURCES.txt
src/django_defaultsite.egg-info/dependency_links.txt
src/django_defaultsite.egg-info/not-zip-safe
src/django_defaultsite.egg-info/top_level.txt