Metadata-Version: 1.0
Name: django-defaultsite
Version: 1.1
Summary: django-defaultsiteSets the Site object in django to something better then example.com.
Home-page: http://oppian.com/labs/django-defaultsite/
Author: Oppian System Ltd
Author-email: matt@oppian.com
License: LICENSE.txt
Keywords: django site example.com
Platform: UNKNOWN
Classifier: Development Status :: 3 - Alpha
Classifier: Environment :: Web Environment
Classifier: Intended Audience :: Developers
Classifier: License :: OSI Approved :: BSD License
Classifier: Operating System :: OS Independent
Classifier: Programming Language :: Python
Classifier: Framework :: Django
